detafield/__init__.py
detafield/abstracet_model.py
detafield/base.py
detafield/descriptor.py
detafield/element.py
detafield/enums.py
detafield/env.py
detafield/functions.py
detafield/json_encoder.py
detafield/regex.py
detafield-0.0.1.dist-info/WHEEL
detafield-0.0.1.dist-info/METADATA
detafield-0.0.1.dist-info/RECORD
