Metadata-Version: 2.1
Name: detafield
Version: 0.0.1
Summary: 
Author: Daniel Arantes
Author-email: arantesdv@me.com
Requires-Python: >=3.9,<4.0
Classifier: Programming Language :: Python :: 3
Classifier: Programming Language :: Python :: 3.10
Classifier: Programming Language :: Python :: 3.9
Requires-Dist: Unidecode (>=1.3.6,<2.0.0)
Requires-Dist: detabase (>=0.2.1,<0.3.0)
